{
    "facebook": {
        "email": "abuhurayrafarhan@gmail.com",
        "password": "vOOogJkbJZaewhFr"
    },
    "amazon": {
        "email": "abuhurayrafarhan@gmail.com",
        "password": "BDIPjvNXzBuOjrR"
    },
    "indent": 4,
    "asda": {
        "email": "abuhurayrafarhan@gmail.com",
        "password": "ucpMksoUduORgWn"
    },
    "insta": {
        "email": "abuhurayrafarhan@gmail.com",
        "password": "GKoDukPnPNSYW"
    },
    "google": {
        "email": "abuhurayrafarhan@gmail.com",
        "password": "XObIaGnGvtqclCU"
    },
    "mecy": {
        "email": "abuhurayrafarhan@gmail.com",
        "password": "STTXqdrsyPRoPe"
    }
}